xbot/__init__.py
xbot/__main__.py
xbot/constants.py
xbot/templates.py
xbot/translate.py
xbot/utils.py
xbot/parsers/__init__.py
xbot/parsers/discord/__init__.py
xbot/parsers/discord/dictionary.py
xbot/parsers/discord/parser.py
xbot/parsers/telegram/__init__.py
xbot/parsers/telegram/dictionary.py
xbot/parsers/telegram/parser.py
x_bot-0.0.2.dist-info/LICENSE
x_bot-0.0.2.dist-info/METADATA
x_bot-0.0.2.dist-info/WHEEL
x_bot-0.0.2.dist-info/top_level.txt
x_bot-0.0.2.dist-info/RECORD
