Metadata-Version: 2.1
Name: x-bot
Version: 0.0.2
Summary: code generator for messaging bot in multiple platforms 
Home-page: https://github.com/SolbiatiAlessandro/xbot
Author: Alessandro Solbiati
Author-email: alessandro.solbiati@gmail.com
License: UNKNOWN
Platform: UNKNOWN
Classifier: Programming Language :: Python :: 3
Classifier: License :: OSI Approved :: MIT License
Classifier: Operating System :: OS Independent
Requires-Python: >=3.6
